libpx/__init__.py
libpx/libpx.py
libpx-9.2.dist-info/METADATA
libpx-9.2.dist-info/WHEEL
libpx-9.2.dist-info/top_level.txt
libpx-9.2.dist-info/RECORD
