Metadata-Version: 2.4
Name: libpx
Version: 9.2
Summary: End-to-end cryptography library including AES, RSA, OAEP, DH, and utilities.
Home-page: https://github.com/azrael1237/crypto
Author: Alfi Keita
Author-email: 
License: MIT
Classifier: Programming Language :: Python :: 3
Classifier: License :: OSI Approved :: MIT License
Classifier: Operating System :: OS Independent
Classifier: Intended Audience :: Developers
Classifier: Topic :: Security :: Cryptography
Requires-Python: >=3.6
Requires-Dist: pyasn1
Dynamic: author
Dynamic: classifier
Dynamic: home-page
Dynamic: license
Dynamic: requires-dist
Dynamic: requires-python
Dynamic: summary
